rqfactor/__init__.py
rqfactor/_dma.cp312-win_amd64.pyd
rqfactor/_version.py
rqfactor/alpha101.cp312-win_amd64.pyd
rqfactor/cross_sectional.cp312-win_amd64.pyd
rqfactor/exception.cp312-win_amd64.pyd
rqfactor/extension.cp312-win_amd64.pyd
rqfactor/fix.cp312-win_amd64.pyd
rqfactor/func.cp312-win_amd64.pyd
rqfactor/indicators.cp312-win_amd64.pyd
rqfactor/interface.cp312-win_amd64.pyd
rqfactor/leaf.cp312-win_amd64.pyd
rqfactor/rolling.cp312-win_amd64.pyd
rqfactor/utils.cp312-win_amd64.pyd
rqfactor/analysis/__init__.py
rqfactor/analysis/_lib.cp312-win_amd64.pyd
rqfactor/analysis/analysis_data_source.cp312-win_amd64.pyd
rqfactor/analysis/analysis_engine.cp312-win_amd64.pyd
rqfactor/analysis/analysis_result.cp312-win_amd64.pyd
rqfactor/analysis/analysis_v2.cp312-win_amd64.pyd
rqfactor/analysis/neutralize.cp312-win_amd64.pyd
rqfactor/analysis/plot.cp312-win_amd64.pyd
rqfactor/analysis/winsorize.cp312-win_amd64.pyd
rqfactor/engine_v2/__init__.py
rqfactor/engine_v2/exec_context.cp312-win_amd64.pyd
rqfactor/engine_v2/exec_engine.cp312-win_amd64.pyd
rqfactor/ext/__init__.py
rqfactor/ext/indicators.cp312-win_amd64.pyd
rqfactor-1.4.7.dist-info/METADATA
rqfactor-1.4.7.dist-info/WHEEL
rqfactor-1.4.7.dist-info/top_level.txt
rqfactor-1.4.7.dist-info/RECORD
