Metadata-Version: 2.1
Name: rqfactor
Version: 1.4.7
Summary: Ricequant factor engine
Home-page: https://www.ricequant.com
Author: ricequant
Author-email: public@ricequant.com
Classifier: Programming Language :: Python
Classifier: Operating System :: Microsoft :: Windows
Classifier: Operating System :: Unix
Classifier: Programming Language :: Python :: 2.7
Classifier: Programming Language :: Python :: 3.4
Classifier: Programming Language :: Python :: 3.5
Classifier: Programming Language :: Python :: 3.6
Classifier: Programming Language :: Python :: 3.7
Classifier: Programming Language :: Python :: 3.8
Requires-Dist: rqdatac >=2.9.1
Requires-Dist: pandas
Requires-Dist: numpy
Requires-Dist: markupsafe
Requires-Dist: patsy >=0.5.1
Requires-Dist: statsmodels >=0.11.1
Requires-Dist: scipy
Requires-Dist: bokeh >=1.4.0
